pygameHat/__init__.py
pygameHat/pygameHat.py
pygameHat-1.1.3.dist-info/METADATA
pygameHat-1.1.3.dist-info/WHEEL
pygameHat-1.1.3.dist-info/top_level.txt
pygameHat-1.1.3.dist-info/RECORD
