Metadata-Version: 2.1
Name: pygameHat
Version: 1.1.3
Summary: Pygame game-making engine
Home-page: UNKNOWN
Author: Wojciech Błajda
Author-email: UNKNOWN
License: UNKNOWN
Keywords: python,engine,pygame,game,maker
Platform: UNKNOWN
Classifier: Development Status :: 4 - Beta
Classifier: Intended Audience :: Developers
Classifier: Programming Language :: Python :: 3
Classifier: Operating System :: Unix
Classifier: Operating System :: MacOS :: MacOS X
Classifier: Operating System :: Microsoft :: Windows
Requires-Dist: pygame
Requires-Dist: pyinstaller
